MANIFEST.in
setup.py
arandomness/__init__.py
arandomness.egg-info/PKG-INFO
arandomness.egg-info/SOURCES.txt
arandomness.egg-info/dependency_links.txt
arandomness.egg-info/not-zip-safe
arandomness.egg-info/top_level.txt
arandomness/argparse/CheckThreads.py
arandomness/argparse/CopyRight.py
arandomness/argparse/Open.py
arandomness/argparse/ParseCommas.py
arandomness/argparse/__init__.py
arandomness/string/__init__.py
arandomness/string/autocorrect.py
arandomness/string/max_substring.py
arandomness/string/print_columns.py
arandomness/trees/__init__.py
arandomness/trees/omnitree.py