Metadata-Version: 1.1
Name: arandomness
Version: 0.1.0
Summary: An arandom assortment of random modules
Home-page: https://github.com/TheOneHyer/arandomness
Author: Alex Hyer
Author-email: theonehyer@gmail.com
License: GPLv3
Download-URL: https://github.com/TheOneHyer/arandomness/tarball/0.1.0
Keywords: arandomness TheOneHyer
Platform: UNKNOWN
Classifier: Development Status :: 5 - Production/Stable
Classifier: Intended Audience :: Developers
Classifier: License :: OSI Approved :: GNU General Public License v3 (GPLv3)
Classifier: Natural Language :: English
Classifier: Operating System :: OS Independent
Classifier: Programming Language :: Python :: 3.6
Classifier: Topic :: Software Development :: Libraries :: Python Modules
Requires: prettytable
